Scrapy16ZhongwenWendang/README.md
Scrapy16ZhongwenWendang/__init__.py
Scrapy16ZhongwenWendang/__main__.py
Scrapy16ZhongwenWendang/file.epub
Scrapy16ZhongwenWendang/index.html
Scrapy16ZhongwenWendang/css/__init__.py
Scrapy16ZhongwenWendang/css/annotations.css
Scrapy16ZhongwenWendang/css/main.css
Scrapy16ZhongwenWendang/css/normalize.css
Scrapy16ZhongwenWendang/css/popup.css
Scrapy16ZhongwenWendang/font/__init__.py
Scrapy16ZhongwenWendang/font/fontello.eot
Scrapy16ZhongwenWendang/font/fontello.svg
Scrapy16ZhongwenWendang/font/fontello.ttf
Scrapy16ZhongwenWendang/font/fontello.woff
Scrapy16ZhongwenWendang/img/__init__.py
Scrapy16ZhongwenWendang/img/annotator-glyph-sprite.png
Scrapy16ZhongwenWendang/img/annotator-icon-sprite.png
Scrapy16ZhongwenWendang/img/apple-touch-icon.png
Scrapy16ZhongwenWendang/img/cancelfullscreen.png
Scrapy16ZhongwenWendang/img/close.png
Scrapy16ZhongwenWendang/img/fullscreen.png
Scrapy16ZhongwenWendang/img/loader.gif
Scrapy16ZhongwenWendang/img/menu-icon.png
Scrapy16ZhongwenWendang/img/save.png
Scrapy16ZhongwenWendang/img/saved.png
Scrapy16ZhongwenWendang/img/settings-s.png
Scrapy16ZhongwenWendang/img/settings.png
Scrapy16ZhongwenWendang/img/star.png
Scrapy16ZhongwenWendang/js/__init__.py
Scrapy16ZhongwenWendang/js/epub.js
Scrapy16ZhongwenWendang/js/epub.min.js
Scrapy16ZhongwenWendang/js/epub.min.map
Scrapy16ZhongwenWendang/js/hooks.min.js
Scrapy16ZhongwenWendang/js/hooks.min.map
Scrapy16ZhongwenWendang/js/reader.js
Scrapy16ZhongwenWendang/js/reader.js.map
Scrapy16ZhongwenWendang/js/reader.min.js
Scrapy16ZhongwenWendang/js/reader.min.map
Scrapy16ZhongwenWendang/js/hooks/__init__.py
Scrapy16ZhongwenWendang/js/hooks/extensions/__init__.py
Scrapy16ZhongwenWendang/js/hooks/extensions/highlight.js
Scrapy16ZhongwenWendang/js/libs/__init__.py
Scrapy16ZhongwenWendang/js/libs/jquery.min.js
Scrapy16ZhongwenWendang/js/libs/localforage.min.js
Scrapy16ZhongwenWendang/js/libs/screenfull.js
Scrapy16ZhongwenWendang/js/libs/screenfull.min.js
scrapy_1_6_zhongwen_wendang-2024.3.4.0.dist-info/METADATA
scrapy_1_6_zhongwen_wendang-2024.3.4.0.dist-info/WHEEL
scrapy_1_6_zhongwen_wendang-2024.3.4.0.dist-info/entry_points.txt
scrapy_1_6_zhongwen_wendang-2024.3.4.0.dist-info/top_level.txt
scrapy_1_6_zhongwen_wendang-2024.3.4.0.dist-info/RECORD
